webmpris-1.1.dist-info/DESCRIPTION.rst
webmpris-1.1.dist-info/pydist.json
webmpris-1.1.dist-info/RECORD
webmpris-1.1.dist-info/METADATA
webmpris-1.1.dist-info/top_level.txt
webmpris-1.1.dist-info/WHEEL
webmpris/views.py
webmpris/urls.py
webmpris/models.py
webmpris/__init__.py
webmpris/tests.py
