Metadata-Version: 2.0
Name: webmpris
Version: 1.1
Summary: REST API to control media players via MPRIS2 interfaces
Home-page: https://github.com/wistful/webmpris
Author: Mikhail Mamrouski
Author-email: wst.public.mail@gmail.com
License: MIT License
Keywords: mpris,dbus,django,rest api
Platform: Unix,
Classifier: Development Status :: 5 - Production/Stable
Classifier: Environment :: Web Environment
Classifier: Framework :: Django
Classifier: Intended Audience :: Developers
Classifier: License :: OSI Approved :: MIT License
Classifier: Programming Language :: Python :: 2.7
Classifier: Topic :: Internet :: WWW/HTTP
Classifier: Topic :: Software Development :: Libraries :: Python Modules
Requires-Dist: pympris
